zippo/__about__.py
zippo/__init__.py
zippo/__main__.py
zippo-1.0.0.dist-info/METADATA
zippo-1.0.0.dist-info/WHEEL
zippo-1.0.0.dist-info/entry_points.txt
zippo-1.0.0.dist-info/licenses/LICENSE.txt
zippo-1.0.0.dist-info/RECORD
