Metadata-Version: 2.4
Name: zippo
Version: 1.0.0
Summary: A command line tool for creating a ZIP archive of a filesystem directory.
Project-URL: Documentation, https://github.com/PolyPik/zippo#readme
Project-URL: Issues, https://github.com/PolyPik/zippo/issues
Project-URL: Source, https://github.com/PolyPik/zippo
Author-email: PolyPik <bighorn_se@yahoo.com>
License-Expression: MIT
License-File: LICENSE.txt
Keywords: ZIP,zip,zip archive,zip file,zip-archive,zip-file,zip_archive,zip_file,ziparchive,zipfile
Classifier: Development Status :: 5 - Production/Stable
Classifier: Programming Language :: Python
Classifier: Programming Language :: Python :: 3.8
Classifier: Programming Language :: Python :: 3.9
Classifier: Programming Language :: Python :: 3.10
Classifier: Programming Language :: Python :: 3.11
Classifier: Programming Language :: Python :: 3.12
Classifier: Programming Language :: Python :: Implementation :: CPython
Classifier: Programming Language :: Python :: Implementation :: PyPy
Classifier: Topic :: System :: Archiving :: Compression
Requires-Python: >=3.8
Requires-Dist: click~=8.1.8
